{
  "job_id": "87077531?type=standard&ref=search-standalone&origin=cardTitle#sol=8b6d0920aca51e0d4901a4e1d8a85dc2d2ab4f16",
  "title": "Data Analyst",
  "company": "Unknown",
  "location": "Unknown",
  "url": "https://www.seek.com.au/job/87077531?type=standard&ref=search-standalone&origin=cardTitle#sol=8b6d0920aca51e0d4901a4e1d8a85dc2d2ab4f16",
  "scraped_at": "2025-09-26T17:40:07.849670",
  "details": {
    "description": "Business Reporting AnalystCopyright AgencySydney NSW14d agoData AnalystCollective Intelligence Group - CIIQ360 Inc.Sydney NSW10d agoBusiness Intelligence & Performance Analyst (Part - time)Multicultural CareBurwood, Sydney NSW14d ago",
    "salary": "Not specified",
    "work_type": "Unknown",
    "classification": ""
  }
}